editor/__init__.py
editor/py.typed
editor-1.6.4.dist-info/LICENSE
editor-1.6.4.dist-info/METADATA
editor-1.6.4.dist-info/WHEEL
editor-1.6.4.dist-info/RECORD
