Metadata-Version: 2.1
Name: editor
Version: 1.6.4
Summary: 🖋 Open the default text editor 🖋
Home-page: https://github.com/rec/editor
License: MIT
Author: Tom Ritchford
Author-email: tom@swirly.com
Requires-Python: >=3.8
Classifier: License :: OSI Approved :: MIT License
Classifier: Programming Language :: Python :: 3
Classifier: Programming Language :: Python :: 3.8
Classifier: Programming Language :: Python :: 3.9
Classifier: Programming Language :: Python :: 3.10
Classifier: Programming Language :: Python :: 3.11
Classifier: Programming Language :: Python :: 3.12
Requires-Dist: runs
Requires-Dist: xmod
Project-URL: Documentation, https://rec.github.io/editor
Project-URL: Repository, https://github.com/rec/editor
